sendevent_getevent_keyboard/LICENSE
sendevent_getevent_keyboard/README.MD
sendevent_getevent_keyboard/__init__.py
sendevent_getevent_keyboard/requirements.txt
sendevent_getevent_keyboard/thirdparty.json
sendevent_getevent_keyboard-0.10.dist-info/LICENSE.rst
sendevent_getevent_keyboard-0.10.dist-info/METADATA
sendevent_getevent_keyboard-0.10.dist-info/WHEEL
sendevent_getevent_keyboard-0.10.dist-info/top_level.txt
sendevent_getevent_keyboard-0.10.dist-info/RECORD
